odoo/addons/stock_picking_type_bypass_reservation/README.rst
odoo/addons/stock_picking_type_bypass_reservation/__init__.py
odoo/addons/stock_picking_type_bypass_reservation/__manifest__.py
odoo/addons/stock_picking_type_bypass_reservation/i18n/es.po
odoo/addons/stock_picking_type_bypass_reservation/i18n/it.po
odoo/addons/stock_picking_type_bypass_reservation/i18n/stock_picking_type_bypass_reservation.pot
odoo/addons/stock_picking_type_bypass_reservation/models/__init__.py
odoo/addons/stock_picking_type_bypass_reservation/models/stock_move.py
odoo/addons/stock_picking_type_bypass_reservation/models/stock_move_line.py
odoo/addons/stock_picking_type_bypass_reservation/models/stock_picking_type.py
odoo/addons/stock_picking_type_bypass_reservation/readme/CONTEXT.md
odoo/addons/stock_picking_type_bypass_reservation/readme/CONTRIBUTORS.md
odoo/addons/stock_picking_type_bypass_reservation/readme/DESCRIPTION.md
odoo/addons/stock_picking_type_bypass_reservation/readme/ROADMAP.md
odoo/addons/stock_picking_type_bypass_reservation/readme/USAGE.md
odoo/addons/stock_picking_type_bypass_reservation/static/description/icon.png
odoo/addons/stock_picking_type_bypass_reservation/static/description/index.html
odoo/addons/stock_picking_type_bypass_reservation/tests/__init__.py
odoo/addons/stock_picking_type_bypass_reservation/tests/test_stock_picking_type.py
odoo/addons/stock_picking_type_bypass_reservation/views/stock_move_line_views.xml
odoo/addons/stock_picking_type_bypass_reservation/views/stock_picking_type_view.xml
odoo_addon_stock_picking_type_bypass_reservation-16.0.1.0.1.2.dist-info/METADATA
odoo_addon_stock_picking_type_bypass_reservation-16.0.1.0.1.2.dist-info/WHEEL
odoo_addon_stock_picking_type_bypass_reservation-16.0.1.0.1.2.dist-info/top_level.txt
odoo_addon_stock_picking_type_bypass_reservation-16.0.1.0.1.2.dist-info/RECORD
